ansible_roles_graph-0.1.0.dist-info/DESCRIPTION.rst
ansible_roles_graph-0.1.0.dist-info/METADATA
ansible_roles_graph-0.1.0.dist-info/RECORD
ansible_roles_graph-0.1.0.dist-info/WHEEL
ansible_roles_graph-0.1.0.dist-info/entry_points.txt
ansible_roles_graph-0.1.0.dist-info/metadata.json
ansible_roles_graph-0.1.0.dist-info/pbr.json
ansible_roles_graph-0.1.0.dist-info/top_level.txt
ansiblerolesgraph/__init__.py
