Metadata-Version: 2.0
Name: ansible-roles-graph
Version: 0.1.0
Summary: Generate a graph of Ansible role dependencies.
Home-page: https://github.com/sebn/ansible-roles-graph
Author: Sebastien Nicouleaud
Author-email: sebastien@nicouleaud.net
License: GPLv3+
Keywords: ansible roles graph
Platform: UNKNOWN
Classifier: Development Status :: 3 - Alpha
Classifier: Environment :: Console
Classifier: Intended Audience :: Developers
Classifier: Intended Audience :: Information Technology
Classifier: Intended Audience :: System Administrators
Classifier: License :: OSI Approved :: GNU General Public License v3 or later (GPLv3+)
Classifier: Natural Language :: English
Classifier: Operating System :: POSIX
Classifier: Programming Language :: Python :: 2.7
Classifier: Topic :: Documentation
Classifier: Topic :: System :: Installation/Setup
Classifier: Topic :: System :: Systems Administration
Classifier: Topic :: Utilities
Requires-Dist: PyYAML
